MANIFEST.in
README.md
setup.py
fabkins/__init__.py
fabkins/app.py
fabkins/commander.py
fabkins/database.py
fabkins/decorators.py
fabkins/default_fabfile.py
fabkins/flaskapp.py
fabkins/gen.py
fabkins/models.py
fabkins/patch.py
fabkins/services.py
fabkins/settings.py
fabkins/tcpsocket.py
fabkins/websocket.py
fabkins.egg-info/PKG-INFO
fabkins.egg-info/SOURCES.txt
fabkins.egg-info/dependency_links.txt
fabkins.egg-info/entry_points.txt
fabkins.egg-info/not-zip-safe
fabkins.egg-info/requires.txt
fabkins.egg-info/top_level.txt
fabkins/static/css/foundation.css
fabkins/static/css/normalize.css
fabkins/static/css/style.css
fabkins/static/css/icons/css/font-awesome-ie7.css
fabkins/static/css/icons/css/font-awesome-ie7.min.css
fabkins/static/css/icons/css/font-awesome.css
fabkins/static/css/icons/css/font-awesome.min.css
fabkins/static/css/icons/font/FontAwesome.otf
fabkins/static/css/icons/font/fontawesome-webfont.eot
fabkins/static/css/icons/font/fontawesome-webfont.svg
fabkins/static/css/icons/font/fontawesome-webfont.ttf
fabkins/static/css/icons/font/fontawesome-webfont.woff
fabkins/static/js/custom.modernizr.js
fabkins/static/js/foundation.min.js
fabkins/static/js/jquery.min.js
fabkins/static/js/ace/ace.js
fabkins/static/js/ace/mode-python.js
fabkins/static/js/ace/theme-solarized_dark.js
fabkins/templates/500.html
fabkins/templates/base.html
fabkins/templates/build.html
fabkins/templates/flashed.html
fabkins/templates/history.html
fabkins/templates/job.html
fabkins/templates/jobs.html
fabkins/templates/login.html
fabkins/templates/navbar.html
fabkins/templates/new_job.html
fabkins/templates/run_form.html
fabkins/templates/watch.html