Metadata-Version: 1.0
Name: fabkins
Version: 0.1.2
Summary: Fabkins, a femto-jenkins based on fabfiles
Home-page: http://github.com/fspot/fabkins
Author: fspot
Author-email: fred@fspot.org
License: MIT
Platform: UNKNOWN
